app/__init__.py
app/formatter.py
app/forms.py
app/middlewares.py
app/settings.py
app/sitemaps.py
app/urls.py
app/views.py
snowebsvg/__init__.py
snowebsvg/abstract.py
snowebsvg/admin.py
snowebsvg/apps.py
snowebsvg/loader.py
snowebsvg/models.py
snowebsvg/settings.py
snowebsvg/management/__init__.py
snowebsvg/management/commands/__init__.py
snowebsvg/management/commands/svg_build.py
snowebsvg/management/commands/svg_clean.py
snowebsvg/management/commands/svg_sync.py
snowebsvg/migrations/0001_initial.py
snowebsvg/migrations/__init__.py
snowebsvg/static/snowebsvg/dist/css/core-0.0.1.css
snowebsvg/static/snowebsvg/dist/css/core-0.0.4.css
snowebsvg/static/snowebsvg/dist/css/core0.0.1.css
snowebsvg/static/snowebsvg/dist/css/essential-0.0.1.css
snowebsvg/static/snowebsvg/dist/css/essential-0.0.4.css
snowebsvg/static/snowebsvg/dist/css/essential0.0.1.css
snowebsvg/static/snowebsvg/dist/js/core-0.0.1.js
snowebsvg/static/snowebsvg/dist/js/core-0.0.4.js
snowebsvg/static/snowebsvg/dist/js/core0.0.1.js
snowebsvg/static/snowebsvg/dist/js/essential-0.0.1.js
snowebsvg/static/snowebsvg/dist/js/essential-0.0.4.js
snowebsvg/static/snowebsvg/dist/js/essential0.0.1.js
snowebsvg/static/snowebsvg/src/scss/core.scss
snowebsvg/static/snowebsvg/src/scss/essential.scss
snowebsvg/static/snowebsvg/src/scss/postcss.config.js
snowebsvg/static/snowebsvg/src/scss/collections/essential/back.scss
snowebsvg/static/snowebsvg/src/scss/common/sizer.scss
snowebsvg/static/snowebsvg/src/scss/common/themes.scss
snowebsvg/static/snowebsvg/src/scss/common/builders/group_hover.scss
snowebsvg/templates/snowebsvg/collections/background/_preview.html
snowebsvg/templates/snowebsvg/collections/background/effect/1.html
snowebsvg/templates/snowebsvg/collections/background/effect/_preview.html
snowebsvg/templates/snowebsvg/collections/background/line/1.html
snowebsvg/templates/snowebsvg/collections/background/line/2.html
snowebsvg/templates/snowebsvg/collections/background/line/_preview.html
snowebsvg-0.0.63.dist-info/LICENSE
snowebsvg-0.0.63.dist-info/METADATA
snowebsvg-0.0.63.dist-info/WHEEL
snowebsvg-0.0.63.dist-info/top_level.txt
snowebsvg-0.0.63.dist-info/RECORD
