Metadata-Version: 2.1
Name: snowebsvg
Version: 0.0.63
Summary: Snoweb SVG
Home-page: https://github.com/Aleksi44/snoweb-svg
Author: Alexis Le Baron
Author-email: hello@snoweb.fr
License: GPL-3.0
Keywords: svg django snoweb
Platform: linux
Classifier: Environment :: Web Environment
Classifier: Intended Audience :: Developers
Classifier: Programming Language :: Python
Classifier: Programming Language :: Python :: 3
Classifier: Programming Language :: Python :: 3.6
Classifier: Programming Language :: Python :: 3.7
Classifier: Programming Language :: Python :: 3.8
Classifier: Operating System :: OS Independent
Classifier: Topic :: Software Development
